{
  "New Taipei City": {
    "chunk_ids": [
      "chunk-2c0392d6b9fa992204426414fd43866d"
    ],
    "count": 1,
    "create_time": 1775134036,
    "update_time": 1775134036,
    "_id": "New Taipei City"
  },
  "Economic Development Department": {
    "chunk_ids": [
      "chunk-2c0392d6b9fa992204426414fd43866d"
    ],
    "count": 1,
    "create_time": 1775134036,
    "update_time": 1775134036,
    "_id": "Economic Development Department"
  },
  "Sheng Xiaorong": {
    "chunk_ids": [
      "chunk-2c0392d6b9fa992204426414fd43866d",
      "chunk-5da080f066020cdaa3662d3326708969"
    ],
    "count": 2,
    "update_time": 1775134040,
    "_id": "Sheng Xiaorong"
  },
  "New Taipei City Crowdfunding Subsidy Program": {
    "chunk_ids": [
      "chunk-2c0392d6b9fa992204426414fd43866d"
    ],
    "count": 1,
    "create_time": 1775134036,
    "update_time": 1775134036,
    "_id": "New Taipei City Crowdfunding Subsidy Program"
  },
  "115 New Taipei City Crowdfunding Subsidy Program": {
    "chunk_ids": [
      "chunk-2c0392d6b9fa992204426414fd43866d"
    ],
    "count": 1,
    "create_time": 1775134036,
    "update_time": 1775134036,
    "_id": "115 New Taipei City Crowdfunding Subsidy Program"
  },
  "AI-Driven Digital Transformation Wave": {
    "chunk_ids": [
      "chunk-2c0392d6b9fa992204426414fd43866d"
    ],
    "count": 1,
    "create_time": 1775134036,
    "update_time": 1775134036,
    "_id": "AI-Driven Digital Transformation Wave"
  },
  "AI Tool Counseling": {
    "chunk_ids": [
      "chunk-2c0392d6b9fa992204426414fd43866d"
    ],
    "count": 1,
    "create_time": 1775134036,
    "update_time": 1775134036,
    "_id": "AI Tool Counseling"
  },
  "Brand Promotion Counseling": {
    "chunk_ids": [
      "chunk-2c0392d6b9fa992204426414fd43866d"
    ],
    "count": 1,
    "create_time": 1775134036,
    "update_time": 1775134036,
    "_id": "Brand Promotion Counseling"
  },
  "Application Briefing Session": {
    "chunk_ids": [
      "chunk-2c0392d6b9fa992204426414fd43866d"
    ],
    "count": 1,
    "create_time": 1775134036,
    "update_time": 1775134036,
    "_id": "Application Briefing Session"
  },
  "Banqiao Youth Career Base": {
    "chunk_ids": [
      "chunk-2c0392d6b9fa992204426414fd43866d"
    ],
    "count": 1,
    "create_time": 1775134036,
    "update_time": 1775134036,
    "_id": "Banqiao Youth Career Base"
  },
  "Huo Wan Design Studio": {
    "chunk_ids": [
      "chunk-2c0392d6b9fa992204426414fd43866d"
    ],
    "count": 1,
    "create_time": 1775134037,
    "update_time": 1775134037,
    "_id": "Huo Wan Design Studio"
  },
  "Taiwanese Can Also Speak": {
    "chunk_ids": [
      "chunk-2c0392d6b9fa992204426414fd43866d"
    ],
    "count": 1,
    "create_time": 1775134037,
    "update_time": 1775134037,
    "_id": "Taiwanese Can Also Speak"
  },
  "NT$245 Million": {
    "chunk_ids": [
      "chunk-2c0392d6b9fa992204426414fd43866d"
    ],
    "count": 1,
    "create_time": 1775134037,
    "update_time": 1775134037,
    "_id": "NT$245 Million"
  },
  "NT$50,000": {
    "chunk_ids": [
      "chunk-2c0392d6b9fa992204426414fd43866d"
    ],
    "count": 1,
    "create_time": 1775134037,
    "update_time": 1775134037,
    "_id": "NT$50,000"
  },
  "NT$6.7 Million": {
    "chunk_ids": [
      "chunk-2c0392d6b9fa992204426414fd43866d"
    ],
    "count": 1,
    "create_time": 1775134037,
    "update_time": 1775134037,
    "_id": "NT$6.7 Million"
  },
  "Crowdfunding Mechanism": {
    "chunk_ids": [
      "chunk-2c0392d6b9fa992204426414fd43866d"
    ],
    "count": 1,
    "create_time": 1775134037,
    "update_time": 1775134037,
    "_id": "Crowdfunding Mechanism"
  },
  "Eligible Enterprises": {
    "chunk_ids": [
      "chunk-2c0392d6b9fa992204426414fd43866d"
    ],
    "count": 1,
    "create_time": 1775134037,
    "update_time": 1775134037,
    "_id": "Eligible Enterprises"
  },
  "Program Website": {
    "chunk_ids": [
      "chunk-2c0392d6b9fa992204426414fd43866d"
    ],
    "count": 1,
    "create_time": 1775134037,
    "update_time": 1775134037,
    "_id": "Program Website"
  },
  "02-2700-9599#102 Hotline": {
    "chunk_ids": [
      "chunk-2c0392d6b9fa992204426414fd43866d"
    ],
    "count": 1,
    "create_time": 1775134037,
    "update_time": 1775134037,
    "_id": "02-2700-9599#102 Hotline"
  },
  "April 14": {
    "chunk_ids": [
      "chunk-2c0392d6b9fa992204426414fd43866d"
    ],
    "count": 1,
    "create_time": 1775134037,
    "update_time": 1775134037,
    "_id": "April 14"
  },
  "October 31, 2026": {
    "chunk_ids": [
      "chunk-2c0392d6b9fa992204426414fd43866d"
    ],
    "count": 1,
    "create_time": 1775134037,
    "update_time": 1775134037,
    "_id": "October 31, 2026"
  },
  "Selected Teams": {
    "chunk_ids": [
      "chunk-2c0392d6b9fa992204426414fd43866d"
    ],
    "count": 1,
    "create_time": 1775134037,
    "update_time": 1775134037,
    "_id": "Selected Teams"
  },
  "Marketing Application Efficiency": {
    "chunk_ids": [
      "chunk-2c0392d6b9fa992204426414fd43866d"
    ],
    "count": 1,
    "create_time": 1775134037,
    "update_time": 1775134037,
    "_id": "Marketing Application Efficiency"
  },
  "Brand Positioning": {
    "chunk_ids": [
      "chunk-2c0392d6b9fa992204426414fd43866d"
    ],
    "count": 1,
    "create_time": 1775134037,
    "update_time": 1775134037,
    "_id": "Brand Positioning"
  },
  "Sustainable Design Concepts": {
    "chunk_ids": [
      "chunk-2c0392d6b9fa992204426414fd43866d"
    ],
    "count": 1,
    "create_time": 1775134037,
    "update_time": 1775134037,
    "_id": "Sustainable Design Concepts"
  },
  "Brand Promotion Lecture": {
    "chunk_ids": [
      "chunk-2c0392d6b9fa992204426414fd43866d"
    ],
    "count": 1,
    "create_time": 1775134037,
    "update_time": 1775134037,
    "_id": "Brand Promotion Lecture"
  },
  "One-on-One Consultant Consultation": {
    "chunk_ids": [
      "chunk-2c0392d6b9fa992204426414fd43866d"
    ],
    "count": 1,
    "create_time": 1775134037,
    "update_time": 1775134037,
    "_id": "One-on-One Consultant Consultation"
  },
  "Initial Crowdfunding Stage": {
    "chunk_ids": [
      "chunk-2c0392d6b9fa992204426414fd43866d"
    ],
    "count": 1,
    "create_time": 1775134037,
    "update_time": 1775134037,
    "_id": "Initial Crowdfunding Stage"
  },
  "85 Teams": {
    "chunk_ids": [
      "chunk-2c0392d6b9fa992204426414fd43866d"
    ],
    "count": 1,
    "create_time": 1775134037,
    "update_time": 1775134037,
    "_id": "85 Teams"
  },
  "Qingming And Children's Day Holiday": {
    "chunk_ids": [
      "chunk-5da080f066020cdaa3662d3326708969"
    ],
    "count": 1,
    "create_time": 1775134040,
    "update_time": 1775134040,
    "_id": "Qingming And Children's Day Holiday"
  },
  "New Taipei City Government Department Of Economic Development": {
    "chunk_ids": [
      "chunk-5da080f066020cdaa3662d3326708969"
    ],
    "count": 1,
    "create_time": 1775134040,
    "update_time": 1775134040,
    "_id": "New Taipei City Government Department Of Economic Development"
  },
  "New Taipei": {
    "chunk_ids": [
      "chunk-5da080f066020cdaa3662d3326708969"
    ],
    "count": 1,
    "create_time": 1775134040,
    "update_time": 1775134040,
    "_id": "New Taipei"
  },
  "Investment Attraction": {
    "chunk_ids": [
      "chunk-5da080f066020cdaa3662d3326708969"
    ],
    "count": 1,
    "create_time": 1775134040,
    "update_time": 1775134040,
    "_id": "Investment Attraction"
  },
  "Public-Private Collaboration": {
    "chunk_ids": [
      "chunk-5da080f066020cdaa3662d3326708969"
    ],
    "count": 1,
    "create_time": 1775134040,
    "update_time": 1775134040,
    "_id": "Public-Private Collaboration"
  },
  "Tamsui Area": {
    "chunk_ids": [
      "chunk-5da080f066020cdaa3662d3326708969"
    ],
    "count": 1,
    "create_time": 1775134040,
    "update_time": 1775134040,
    "_id": "Tamsui Area"
  },
  "Fullon Hotel Tamsui Fishermen's Wharf": {
    "chunk_ids": [
      "chunk-5da080f066020cdaa3662d3326708969"
    ],
    "count": 1,
    "create_time": 1775134040,
    "update_time": 1775134040,
    "_id": "Fullon Hotel Tamsui Fishermen's Wharf"
  },
  "Spring Tour Tamsui New Style": {
    "chunk_ids": [
      "chunk-5da080f066020cdaa3662d3326708969"
    ],
    "count": 1,
    "create_time": 1775134040,
    "update_time": 1775134040,
    "_id": "Spring Tour Tamsui New Style"
  },
  "Huwei Art And Cultural Leisure Park": {
    "chunk_ids": [
      "chunk-5da080f066020cdaa3662d3326708969"
    ],
    "count": 1,
    "create_time": 1775134040,
    "update_time": 1775134040,
    "_id": "Huwei Art And Cultural Leisure Park"
  },
  "Golden Tulip Fabland Hotel": {
    "chunk_ids": [
      "chunk-5da080f066020cdaa3662d3326708969"
    ],
    "count": 1,
    "create_time": 1775134040,
    "update_time": 1775134040,
    "_id": "Golden Tulip Fabland Hotel"
  },
  "Sandbag Fun Grab": {
    "chunk_ids": [
      "chunk-5da080f066020cdaa3662d3326708969"
    ],
    "count": 1,
    "create_time": 1775134040,
    "update_time": 1775134040,
    "_id": "Sandbag Fun Grab"
  },
  "Lihpao Plaza": {
    "chunk_ids": [
      "chunk-5da080f066020cdaa3662d3326708969"
    ],
    "count": 1,
    "create_time": 1775134040,
    "update_time": 1775134040,
    "_id": "Lihpao Plaza"
  },
  "Banqiao Area": {
    "chunk_ids": [
      "chunk-5da080f066020cdaa3662d3326708969"
    ],
    "count": 1,
    "create_time": 1775134040,
    "update_time": 1775134040,
    "_id": "Banqiao Area"
  },
  "Hilton Taipei Sinban": {
    "chunk_ids": [
      "chunk-5da080f066020cdaa3662d3326708969"
    ],
    "count": 1,
    "create_time": 1775134040,
    "update_time": 1775134040,
    "_id": "Hilton Taipei Sinban"
  },
  "Caesar Park Hotel Banqiao": {
    "chunk_ids": [
      "chunk-5da080f066020cdaa3662d3326708969"
    ],
    "count": 1,
    "create_time": 1775134040,
    "update_time": 1775134040,
    "_id": "Caesar Park Hotel Banqiao"
  },
  "Hotel Cham Cham Taipei": {
    "chunk_ids": [
      "chunk-5da080f066020cdaa3662d3326708969"
    ],
    "count": 1,
    "create_time": 1775134040,
    "update_time": 1775134040,
    "_id": "Hotel Cham Cham Taipei"
  },
  "Honhui Plaza": {
    "chunk_ids": [
      "chunk-5da080f066020cdaa3662d3326708969"
    ],
    "count": 1,
    "create_time": 1775134040,
    "update_time": 1775134040,
    "_id": "Honhui Plaza"
  },
  "Showtime Cinemas Lifestyle Store Shulin": {
    "chunk_ids": [
      "chunk-5da080f066020cdaa3662d3326708969"
    ],
    "count": 1,
    "create_time": 1775134040,
    "update_time": 1775134040,
    "_id": "Showtime Cinemas Lifestyle Store Shulin"
  },
  "MITSUI OUTLET PARK Linkou": {
    "chunk_ids": [
      "chunk-5da080f066020cdaa3662d3326708969"
    ],
    "count": 1,
    "create_time": 1775134040,
    "update_time": 1775134040,
    "_id": "MITSUI OUTLET PARK Linkou"
  },
  "Commercial Investment Projects": {
    "chunk_ids": [
      "chunk-5da080f066020cdaa3662d3326708969"
    ],
    "count": 1,
    "create_time": 1775134040,
    "update_time": 1775134040,
    "_id": "Commercial Investment Projects"
  },
  "Parent-Child Activities": {
    "chunk_ids": [
      "chunk-5da080f066020cdaa3662d3326708969"
    ],
    "count": 1,
    "create_time": 1775134040,
    "update_time": 1775134040,
    "_id": "Parent-Child Activities"
  },
  "Holiday Exclusive Offers": {
    "chunk_ids": [
      "chunk-5da080f066020cdaa3662d3326708969"
    ],
    "count": 1,
    "create_time": 1775134040,
    "update_time": 1775134040,
    "_id": "Holiday Exclusive Offers"
  },
  "Mixed-Use Complexes": {
    "chunk_ids": [
      "chunk-5da080f066020cdaa3662d3326708969"
    ],
    "count": 1,
    "create_time": 1775134040,
    "update_time": 1775134040,
    "_id": "Mixed-Use Complexes"
  },
  "Local Industry Development": {
    "chunk_ids": [
      "chunk-5da080f066020cdaa3662d3326708969"
    ],
    "count": 1,
    "create_time": 1775134040,
    "update_time": 1775134040,
    "_id": "Local Industry Development"
  },
  "Employment Opportunities": {
    "chunk_ids": [
      "chunk-5da080f066020cdaa3662d3326708969"
    ],
    "count": 1,
    "create_time": 1775134040,
    "update_time": 1775134040,
    "_id": "Employment Opportunities"
  },
  "Economic Growth Momentum": {
    "chunk_ids": [
      "chunk-5da080f066020cdaa3662d3326708969"
    ],
    "count": 1,
    "create_time": 1775134040,
    "update_time": 1775134040,
    "_id": "Economic Growth Momentum"
  },
  "Shopping Credits": {
    "chunk_ids": [
      "chunk-5da080f066020cdaa3662d3326708969"
    ],
    "count": 1,
    "create_time": 1775134040,
    "update_time": 1775134040,
    "_id": "Shopping Credits"
  },
  "Entertainment Vouchers": {
    "chunk_ids": [
      "chunk-5da080f066020cdaa3662d3326708969"
    ],
    "count": 1,
    "create_time": 1775134040,
    "update_time": 1775134040,
    "_id": "Entertainment Vouchers"
  },
  "Food Vouchers": {
    "chunk_ids": [
      "chunk-5da080f066020cdaa3662d3326708969"
    ],
    "count": 1,
    "create_time": 1775134040,
    "update_time": 1775134040,
    "_id": "Food Vouchers"
  },
  "Brand Gifts": {
    "chunk_ids": [
      "chunk-5da080f066020cdaa3662d3326708969"
    ],
    "count": 1,
    "create_time": 1775134040,
    "update_time": 1775134040,
    "_id": "Brand Gifts"
  },
  "Prize Draw Opportunity": {
    "chunk_ids": [
      "chunk-5da080f066020cdaa3662d3326708969"
    ],
    "count": 1,
    "create_time": 1775134040,
    "update_time": 1775134040,
    "_id": "Prize Draw Opportunity"
  },
  "Accommodation Value For Money": {
    "chunk_ids": [
      "chunk-5da080f066020cdaa3662d3326708969"
    ],
    "count": 1,
    "create_time": 1775134040,
    "update_time": 1775134040,
    "_id": "Accommodation Value For Money"
  },
  "Official Websites": {
    "chunk_ids": [
      "chunk-5da080f066020cdaa3662d3326708969"
    ],
    "count": 1,
    "create_time": 1775134041,
    "update_time": 1775134041,
    "_id": "Official Websites"
  },
  "Discount Voucher": {
    "chunk_ids": [
      "chunk-5da080f066020cdaa3662d3326708969"
    ],
    "count": 1,
    "create_time": 1775134041,
    "update_time": 1775134041,
    "_id": "Discount Voucher"
  },
  "DIY Experience": {
    "chunk_ids": [
      "chunk-5da080f066020cdaa3662d3326708969"
    ],
    "count": 1,
    "create_time": 1775134041,
    "update_time": 1775134041,
    "_id": "DIY Experience"
  },
  "Game Vouchers": {
    "chunk_ids": [
      "chunk-5da080f066020cdaa3662d3326708969"
    ],
    "count": 1,
    "create_time": 1775134041,
    "update_time": 1775134041,
    "_id": "Game Vouchers"
  },
  "Scratch-Painting Experience": {
    "chunk_ids": [
      "chunk-5da080f066020cdaa3662d3326708969"
    ],
    "count": 1,
    "create_time": 1775134041,
    "update_time": 1775134041,
    "_id": "Scratch-Painting Experience"
  }
}